{
	"_version" : "0",

	"device_info" :  {
		"device_id" : "TEXT",
		"is_registered" : "INTEGER"
	},

	"ecu_serials" : {
		"serial" : "TEXT",
		"hardware_id" : "TEXT",
		"is_primary" : "INTEGER"
	},

	"tls_creds" : {
		"ca_cert" : "BLOB",
		"ca_cert_format" : "TEXT",
		"client_cert" : "BLOB",
		"client_cert_format" : "TEXT",
		"client_pkey" : "BLOB",
		"client_pkey_format" : "TEXT"
	},

	"root_meta" : {
		"root" : "BLOB",
		"meta_format" : "TEXT",
		"director" : "INTEGER",
		"version" : "INTEGER"
	},

	"meta" : {
		"director_targets" : "BLOB",
		"director_targets_format" : "TEXT",
		"image_targets" : "BLOB",
		"image_targets_format" : "TEXT",
		"image_timestamp" : "BLOB",
		"image_timestamp_format" : "TEXT",
		"image_snapshot" : "BLOB",
		"image_snapshot_format" : "TEXT",
		"time" : "BLOB",
		"time_format" : "TEXT"
	},

	"primary_image" : {
		"filepath" : "TEXT"
	}


}
